{
    "/js/app.js": "/js/app.js",
    "/css/emoji.css": "/css/emoji.css",
    "/css/spinkit.css": "/css/spinkit.css",
    "/css/app.css": "/css/app.css",
    "/css/bootstrap-tagsinput.css": "/css/bootstrap-tagsinput.css",
    "/css/owl.carousel.min.css": "/css/owl.carousel.min.css",
    "/css/owl.theme.default.min.css": "/css/owl.theme.default.min.css",
    "/css/green-audio-player.css": "/css/green-audio-player.css",
    "/js/bootstrap-tagsinput.js": "/js/bootstrap-tagsinput.js",
    "/js/broadcaster.js": "/js/broadcaster.js",
    "/js/channels.js": "/js/channels.js",
    "/js/custom.js": "/js/custom.js",
    "/js/emoji/config.js": "/js/emoji/config.js",
    "/js/emoji/emoji-picker.js": "/js/emoji/emoji-picker.js",
    "/js/emoji/jquery.emojiarea.js": "/js/emoji/jquery.emojiarea.js",
    "/js/emoji/util.js": "/js/emoji/util.js",
    "/js/green-audio-player.js": "/js/green-audio-player.js",
    "/js/history.js": "/js/history.js",
    "/js/live-streams.js": "/js/live-streams.js",
    "/js/loademoji.js": "/js/loademoji.js",
    "/js/login.js": "/js/login.js",
    "/js/owl.carousel.min.js": "/js/owl.carousel.min.js",
    "/js/podcast.js": "/js/podcast.js",
    "/js/search.js": "/js/search.js",
    "/js/settings.js": "/js/settings.js",
    "/js/view.js": "/js/view.js",
    "/js/viewer.js": "/js/viewer.js"
}
